{"type": "FeatureCollection", "crs": {"type": "name", "properties": {"name": "EPSG:4326"}}, "features": [{"type": "Feature", "id": 533683, "geometry": {"type": "Point", "coordinates": [-75.336739, 45.813586]}, "properties": {"OBJECTID": 533683, "GlobalID": "7c4c44f3-4425-4c0e-b1b8-4e4df32a4890", "idInterruption": "LAV-I-38195-1", "panneMajeure": 0}}, {"type": "Feature", "id": 539656, "geometry": {"type": "Point", "coordinates": [-71.189714, 46.864766]}, "properties": {"OBJECTID": 539656, "GlobalID": "6a52d27f-d554-4d3c-a363-982f3ec06e7c", "idInterruption": "ORL-I-18934-1", "panneMajeure": 0}}, {"type": "Feature", "id": 540397, "geometry": {"type": "Point", "coordinates": [-73.501748, 45.522907]}, "properties": {"OBJECTID": 540397, "GlobalID": "36992864-a6f6-4040-a456-acdf71248476", "idInterruption": "SEI-I-44099-1", "panneMajeure": 0}}, {"type": "Feature", "id": 540435, "geometry": {"type": "Point", "coordinates": [-75.093869, 45.846154]}, "properties": {"OBJECTID": 540435, "GlobalID": "dcf4a2a1-ea43-4359-924e-c033ea8c0bd5", "idInterruption": "LAV-I-44789-1", "panneMajeure": 0}}, {"type": "Feature", "id": 540498, "geometry": {"type": "Point", "coordinates": [-75.631481, 45.669747]}, "properties": {"OBJECTID": 540498, "GlobalID": "35bb2f9a-7e00-42da-b39c-9d43f1cacc99", "idInterruption": "LAV-I-44869-1", "panneMajeure": 0}}, {"type": "Feature", "id": 540535, "geometry": {"type": "Point", "coordinates": [-71.849418, 45.794031]}, "properties": {"OBJECTID": 540535, "GlobalID": "cd04de28-8087-48dd-a586-e85959e94739", "idInterruption": "SEI-I-44209-1", "panneMajeure": 0}}, {"type": "Feature", "id": 540536, "geometry": {"type": "Point", "coordinates": [-72.751733, 45.398853]}, "properties": {"OBJECTID": 540536, "GlobalID": "ff1547db-5c82-4a97-99f2-6e5457ebc848", "idInterruption": "SEI-I-44210-1", "panneMajeure": 0}}, {"type": "Feature", "id": 540538, "geometry": {"type": "Point", "coordinates": [-73.501842, 45.523064]}, "properties": {"OBJECTID": 540538, "GlobalID": "3b5c097c-1d8d-40bf-88f5-7f8a1fef53ad", "idInterruption": "SEI-I-44213-1", "panneMajeure": 0}}, {"type": "Feature", "id": 540539, "geometry": {"type": "Point", "coordinates": [-75.738146, 45.430864]}, "properties": {"OBJECTID": 540539, "GlobalID": "4d41ff4c-da2a-4747-a9f6-41c6b8456480", "idInterruption": "LAV-I-44890-1", "panneMajeure": 0}}, {"type": "Feature", "id": 540550, "geometry": {"type": "Point", "coordinates": [-72.752808, 45.398991]}, "properties": {"OBJECTID": 540550, "GlobalID": "d7f25687-28ce-40f6-b1a7-ddb7fcc11e91", "idInterruption": "SEI-I-44228-1", "panneMajeure": 0}}, {"type": "Feature", "id": 540577, "geometry": {"type": "Point", "coordinates": [-72.422846, 45.42427]}, "properties": {"OBJECTID": 540577, "GlobalID": "baa91f60-514c-4aef-bb47-98226f8c5b15", "idInterruption": "SEI-I-44252-1", "panneMajeure": 0}}, {"type": "Feature", "id": 540578, "geometry": {"type": "Point", "coordinates": [-72.436132, 45.400094]}, "properties": {"OBJECTID": 540578, "GlobalID": "3a1685de-dd3f-4426-9848-a78b92a02ece", "idInterruption": "SEI-I-44254-1", "panneMajeure": 0}}, {"type": "Feature", "id": 540579, "geometry": {"type": "Point", "coordinates": [-74.110426, 45.950306]}, "properties": {"OBJECTID": 540579, "GlobalID": "d6ef9ce5-8f7d-47f2-8aba-6307807cb9d6", "idInterruption": "LAV-I-44893-1", "panneMajeure": 0}}]}