{"type": "FeatureCollection", "crs": {"type": "name", "properties": {"name": "EPSG:4326"}}, "features": [{"type": "Feature", "id": 533683, "geometry": {"type": "Point", "coordinates": [-75.336739, 45.813586]}, "properties": {"OBJECTID": 533683, "GlobalID": "7c4c44f3-4425-4c0e-b1b8-4e4df32a4890", "idInterruption": "LAV-I-38195-1", "panneMajeure": 0}}, {"type": "Feature", "id": 539656, "geometry": {"type": "Point", "coordinates": [-71.189714, 46.864766]}, "properties": {"OBJECTID": 539656, "GlobalID": "6a52d27f-d554-4d3c-a363-982f3ec06e7c", "idInterruption": "ORL-I-18934-1", "panneMajeure": 0}}, {"type": "Feature", "id": 541307, "geometry": {"type": "Point", "coordinates": [-73.88106, 45.56625]}, "properties": {"OBJECTID": 541307, "GlobalID": "11132115-769a-4e0b-9d7e-66a621c7cc9b", "idInterruption": "LAV-I-45891-1", "panneMajeure": 0}}, {"type": "Feature", "id": 541365, "geometry": {"type": "Point", "coordinates": [-73.569436, 45.471281]}, "properties": {"OBJECTID": 541365, "GlobalID": "0f04888d-766c-44d3-bca1-8306fac19ae4", "idInterruption": "NOR-I-37784-1", "panneMajeure": 0}}, {"type": "Feature", "id": 541367, "geometry": {"type": "Point", "coordinates": [-73.564055, 45.464402]}, "properties": {"OBJECTID": 541367, "GlobalID": "4b9afc87-6abc-4e9e-8d5e-c59785737bda", "idInterruption": "NOR-I-37792-1", "panneMajeure": 0}}, {"type": "Feature", "id": 541371, "geometry": {"type": "Point", "coordinates": [-73.083688, 45.026666]}, "properties": {"OBJECTID": 541371, "GlobalID": "3c6bc1f3-d06b-473e-8d0d-bea0d642ccab", "idInterruption": "SEI-I-45102-1", "panneMajeure": 0}}, {"type": "Feature", "id": 541385, "geometry": {"type": "Point", "coordinates": [-73.910923, 45.564952]}, "properties": {"OBJECTID": 541385, "GlobalID": "1fc1dd35-56ff-4110-9b9b-920ecf027501", "idInterruption": "LAV-I-45971-1", "panneMajeure": 0}}, {"type": "Feature", "id": 541392, "geometry": {"type": "Point", "coordinates": [-73.570227, 45.554263]}, "properties": {"OBJECTID": 541392, "GlobalID": "8236481a-98c2-4f6a-bdb3-f18ddc997041", "idInterruption": "NOR-I-37815-1", "panneMajeure": 0}}, {"type": "Feature", "id": 541394, "geometry": {"type": "Point", "coordinates": [-73.637983, 45.489389]}, "properties": {"OBJECTID": 541394, "GlobalID": "bb53431b-9359-49e6-97e2-d9093d9c0593", "idInterruption": "NOR-I-37827-1", "panneMajeure": 0}}, {"type": "Feature", "id": 541395, "geometry": {"type": "Point", "coordinates": [-71.852173, 46.877414]}, "properties": {"OBJECTID": 541395, "GlobalID": "dc0168e0-08bd-4f46-afc0-751d23cdbaf2", "idInterruption": "ORL-I-19784-1", "panneMajeure": 0}}, {"type": "Feature", "id": 541399, "geometry": {"type": "Point", "coordinates": [-73.900129, 45.56035]}, "properties": {"OBJECTID": 541399, "GlobalID": "5578243d-0caf-4849-b767-b58ebfe37bb0", "idInterruption": "LAV-I-45985-1", "panneMajeure": 0}}, {"type": "Feature", "id": 541404, "geometry": {"type": "Point", "coordinates": [-73.450224, 45.538538]}, "properties": {"OBJECTID": 541404, "GlobalID": "711e1e5b-5344-4ec3-b4f9-36c56a866d54", "idInterruption": "SEI-I-45125-1", "panneMajeure": 0}}, {"type": "Feature", "id": 541405, "geometry": {"type": "Point", "coordinates": [-76.198643, 46.211383]}, "properties": {"OBJECTID": 541405, "GlobalID": "e1c78985-8ecb-4f54-8f3c-858d56274bbf", "idInterruption": "LAV-I-45992-1", "panneMajeure": 0}}]}