{"type": "FeatureCollection", "crs": {"type": "name", "properties": {"name": "EPSG:4326"}}, "features": [{"type": "Feature", "id": 533683, "geometry": {"type": "Point", "coordinates": [-75.336739, 45.813586]}, "properties": {"OBJECTID": 533683, "GlobalID": "7c4c44f3-4425-4c0e-b1b8-4e4df32a4890", "idInterruption": "LAV-I-38195-1", "panneMajeure": 0}}, {"type": "Feature", "id": 539656, "geometry": {"type": "Point", "coordinates": [-71.189714, 46.864766]}, "properties": {"OBJECTID": 539656, "GlobalID": "6a52d27f-d554-4d3c-a363-982f3ec06e7c", "idInterruption": "ORL-I-18934-1", "panneMajeure": 0}}, {"type": "Feature", "id": 540435, "geometry": {"type": "Point", "coordinates": [-75.093869, 45.846154]}, "properties": {"OBJECTID": 540435, "GlobalID": "dcf4a2a1-ea43-4359-924e-c033ea8c0bd5", "idInterruption": "LAV-I-44789-1", "panneMajeure": 0}}, {"type": "Feature", "id": 540498, "geometry": {"type": "Point", "coordinates": [-75.631481, 45.669747]}, "properties": {"OBJECTID": 540498, "GlobalID": "35bb2f9a-7e00-42da-b39c-9d43f1cacc99", "idInterruption": "LAV-I-44869-1", "panneMajeure": 0}}, {"type": "Feature", "id": 540836, "geometry": {"type": "Point", "coordinates": [-73.633343, 46.222327]}, "properties": {"OBJECTID": 540836, "GlobalID": "28724d42-6f9a-4ef9-9767-f41ec10d32e7", "idInterruption": "LAV-I-45189-1", "panneMajeure": 0}}, {"type": "Feature", "id": 540870, "geometry": {"type": "Point", "coordinates": [-69.865185, 47.017122]}, "properties": {"OBJECTID": 540870, "GlobalID": "98c5d440-7561-4af1-8e34-1c04b60b9b61", "idInterruption": "ORL-I-19374-1", "panneMajeure": 0}}, {"type": "Feature", "id": 540875, "geometry": {"type": "Point", "coordinates": [-73.85166, 45.18983]}, "properties": {"OBJECTID": 540875, "GlobalID": "e40dd305-a26a-436e-a85f-5a7f0fbf4640", "idInterruption": "SEI-I-44553-2", "panneMajeure": 0}}, {"type": "Feature", "id": 540893, "geometry": {"type": "Point", "coordinates": [-71.356756, 46.384794]}, "properties": {"OBJECTID": 540893, "GlobalID": "7f352f9e-b672-4be7-85ec-b957031af1e4", "idInterruption": "ORL-I-19410-1", "panneMajeure": 0}}, {"type": "Feature", "id": 540907, "geometry": {"type": "Point", "coordinates": [-72.524886, 48.841663]}, "properties": {"OBJECTID": 540907, "GlobalID": "826a2137-5571-4b7c-89e3-2774e7615b1f", "idInterruption": "MAT-I-7805-1", "panneMajeure": 0}}, {"type": "Feature", "id": 540917, "geometry": {"type": "Point", "coordinates": [-72.348154, 45.330402]}, "properties": {"OBJECTID": 540917, "GlobalID": "ce1f3cd1-9aba-439c-a517-5615cb3c25bf", "idInterruption": "SEI-I-44628-1", "panneMajeure": 0}}, {"type": "Feature", "id": 540919, "geometry": {"type": "Point", "coordinates": [-72.021892, 46.757406]}, "properties": {"OBJECTID": 540919, "GlobalID": "f7cb3621-44c8-4744-b3dd-4b05d107a02e", "idInterruption": "ORL-I-19451-1", "panneMajeure": 0}}, {"type": "Feature", "id": 540925, "geometry": {"type": "Point", "coordinates": [-72.747522, 46.003323]}, "properties": {"OBJECTID": 540925, "GlobalID": "5e03113b-ef2f-4b60-84e3-f25bb2584152", "idInterruption": "SEI-I-44639-1", "panneMajeure": 0}}, {"type": "Feature", "id": 540926, "geometry": {"type": "Point", "coordinates": [-72.749892, 45.397239]}, "properties": {"OBJECTID": 540926, "GlobalID": "47423319-b05f-40dd-a385-03c3a7f82a65", "idInterruption": "SEI-I-44634-1", "panneMajeure": 0}}, {"type": "Feature", "id": 540929, "geometry": {"type": "Point", "coordinates": [-74.11356, 45.978321]}, "properties": {"OBJECTID": 540929, "GlobalID": "3f3b5af0-5bda-441b-a2f5-4a331d64cc3e", "idInterruption": "LAV-I-45347-1", "panneMajeure": 0}}, {"type": "Feature", "id": 540931, "geometry": {"type": "Point", "coordinates": [-75.407451, 46.383352]}, "properties": {"OBJECTID": 540931, "GlobalID": "79078491-d304-4624-beac-5948acf23ebc", "idInterruption": "LAV-I-45366-1", "panneMajeure": 0}}, {"type": "Feature", "id": 540932, "geometry": {"type": "Point", "coordinates": [-73.61453, 45.511404]}, "properties": {"OBJECTID": 540932, "GlobalID": "57d5e4c9-1cc6-4be2-b35d-78650643f974", "idInterruption": "NOR-I-37387-1", "panneMajeure": 0}}, {"type": "Feature", "id": 540934, "geometry": {"type": "Point", "coordinates": [-73.609341, 45.511719]}, "properties": {"OBJECTID": 540934, "GlobalID": "4be2321b-6719-43c3-9ab9-1c72a4f248c4", "idInterruption": "NOR-I-37388-1", "panneMajeure": 0}}, {"type": "Feature", "id": 540935, "geometry": {"type": "Point", "coordinates": [-73.354652, 45.313336]}, "properties": {"OBJECTID": 540935, "GlobalID": "6de64270-c363-41c4-aabf-b16e6e375255", "idInterruption": "SEI-I-44649-1", "panneMajeure": 0}}, {"type": "Feature", "id": 540937, "geometry": {"type": "Point", "coordinates": [-73.618849, 45.511689]}, "properties": {"OBJECTID": 540937, "GlobalID": "c00b64f4-1ad7-4ea6-b4b1-92e8271593e2", "idInterruption": "NOR-I-37396-1", "panneMajeure": 0}}]}