{"type": "FeatureCollection", "crs": {"type": "name", "properties": {"name": "EPSG:4326"}}, "features": [{"type": "Feature", "id": 533683, "geometry": {"type": "Point", "coordinates": [-75.336739, 45.813586]}, "properties": {"OBJECTID": 533683, "GlobalID": "7c4c44f3-4425-4c0e-b1b8-4e4df32a4890", "idInterruption": "LAV-I-38195-1", "panneMajeure": 0}}, {"type": "Feature", "id": 539656, "geometry": {"type": "Point", "coordinates": [-71.189714, 46.864766]}, "properties": {"OBJECTID": 539656, "GlobalID": "6a52d27f-d554-4d3c-a363-982f3ec06e7c", "idInterruption": "ORL-I-18934-1", "panneMajeure": 0}}, {"type": "Feature", "id": 540435, "geometry": {"type": "Point", "coordinates": [-75.093869, 45.846154]}, "properties": {"OBJECTID": 540435, "GlobalID": "dcf4a2a1-ea43-4359-924e-c033ea8c0bd5", "idInterruption": "LAV-I-44789-1", "panneMajeure": 0}}, {"type": "Feature", "id": 540498, "geometry": {"type": "Point", "coordinates": [-75.631481, 45.669747]}, "properties": {"OBJECTID": 540498, "GlobalID": "35bb2f9a-7e00-42da-b39c-9d43f1cacc99", "idInterruption": "LAV-I-44869-1", "panneMajeure": 0}}, {"type": "Feature", "id": 540917, "geometry": {"type": "Point", "coordinates": [-72.348154, 45.330402]}, "properties": {"OBJECTID": 540917, "GlobalID": "ce1f3cd1-9aba-439c-a517-5615cb3c25bf", "idInterruption": "SEI-I-44628-1", "panneMajeure": 0}}, {"type": "Feature", "id": 540956, "geometry": {"type": "Point", "coordinates": [-71.203775, 45.733446]}, "properties": {"OBJECTID": 540956, "GlobalID": "0a02f9d9-7398-4c99-8d71-8a8a6757da05", "idInterruption": "ORL-I-19476-1", "panneMajeure": 0}}, {"type": "Feature", "id": 540963, "geometry": {"type": "Point", "coordinates": [-72.17099, 45.39561]}, "properties": {"OBJECTID": 540963, "GlobalID": "c4af7b2c-10eb-404f-a6dc-6c083d43e48a", "idInterruption": "SEI-I-44676-1", "panneMajeure": 0}}, {"type": "Feature", "id": 540966, "geometry": {"type": "Point", "coordinates": [-72.75036, 45.400367]}, "properties": {"OBJECTID": 540966, "GlobalID": "ba209ae8-02b2-4ea6-8704-96ddf4d90ab3", "idInterruption": "SEI-I-44681-1", "panneMajeure": 0}}]}