{"type": "FeatureCollection", "crs": {"type": "name", "properties": {"name": "EPSG:4326"}}, "features": [{"type": "Feature", "id": 533683, "geometry": {"type": "Point", "coordinates": [-75.336739, 45.813586]}, "properties": {"OBJECTID": 533683, "GlobalID": "7c4c44f3-4425-4c0e-b1b8-4e4df32a4890", "idInterruption": "LAV-I-38195-1", "panneMajeure": 0}}, {"type": "Feature", "id": 539656, "geometry": {"type": "Point", "coordinates": [-71.189714, 46.864766]}, "properties": {"OBJECTID": 539656, "GlobalID": "6a52d27f-d554-4d3c-a363-982f3ec06e7c", "idInterruption": "ORL-I-18934-1", "panneMajeure": 0}}, {"type": "Feature", "id": 540435, "geometry": {"type": "Point", "coordinates": [-75.093869, 45.846154]}, "properties": {"OBJECTID": 540435, "GlobalID": "dcf4a2a1-ea43-4359-924e-c033ea8c0bd5", "idInterruption": "LAV-I-44789-1", "panneMajeure": 0}}, {"type": "Feature", "id": 540498, "geometry": {"type": "Point", "coordinates": [-75.631481, 45.669747]}, "properties": {"OBJECTID": 540498, "GlobalID": "35bb2f9a-7e00-42da-b39c-9d43f1cacc99", "idInterruption": "LAV-I-44869-1", "panneMajeure": 0}}, {"type": "Feature", "id": 540917, "geometry": {"type": "Point", "coordinates": [-72.348154, 45.330402]}, "properties": {"OBJECTID": 540917, "GlobalID": "ce1f3cd1-9aba-439c-a517-5615cb3c25bf", "idInterruption": "SEI-I-44628-1", "panneMajeure": 0}}, {"type": "Feature", "id": 540972, "geometry": {"type": "Point", "coordinates": [-70.799608, 48.00711]}, "properties": {"OBJECTID": 540972, "GlobalID": "4865c558-2b0a-4258-8140-4664f2906861", "idInterruption": "MAT-I-7836-1", "panneMajeure": 0}}, {"type": "Feature", "id": 540975, "geometry": {"type": "Point", "coordinates": [-73.561567, 45.508231]}, "properties": {"OBJECTID": 540975, "GlobalID": "fa0d28a2-a0c1-4111-9f90-5689d9475bef", "idInterruption": "NOR-I-37447-1", "panneMajeure": 0}}, {"type": "Feature", "id": 540997, "geometry": {"type": "Point", "coordinates": [-76.198279, 46.224362]}, "properties": {"OBJECTID": 540997, "GlobalID": "52def1bd-648a-4535-9ccc-6a8e3cad8ae8", "idInterruption": "LAV-I-45474-1", "panneMajeure": 0}}]}