{"type": "FeatureCollection", "crs": {"type": "name", "properties": {"name": "EPSG:4326"}}, "features": [{"type": "Feature", "id": 533683, "geometry": {"type": "Point", "coordinates": [-75.336739, 45.813586]}, "properties": {"OBJECTID": 533683, "GlobalID": "7c4c44f3-4425-4c0e-b1b8-4e4df32a4890", "idInterruption": "LAV-I-38195-1", "panneMajeure": 0}}, {"type": "Feature", "id": 539656, "geometry": {"type": "Point", "coordinates": [-71.189714, 46.864766]}, "properties": {"OBJECTID": 539656, "GlobalID": "6a52d27f-d554-4d3c-a363-982f3ec06e7c", "idInterruption": "ORL-I-18934-1", "panneMajeure": 0}}, {"type": "Feature", "id": 541367, "geometry": {"type": "Point", "coordinates": [-73.564055, 45.464402]}, "properties": {"OBJECTID": 541367, "GlobalID": "4b9afc87-6abc-4e9e-8d5e-c59785737bda", "idInterruption": "NOR-I-37792-1", "panneMajeure": 0}}, {"type": "Feature", "id": 541425, "geometry": {"type": "Point", "coordinates": [-72.842662, 46.040324]}, "properties": {"OBJECTID": 541425, "GlobalID": "5746deaf-b431-4e77-8801-5ce417c3494d", "idInterruption": "SEI-I-45156-1", "panneMajeure": 0}}, {"type": "Feature", "id": 541431, "geometry": {"type": "Point", "coordinates": [-73.24404, 45.335378]}, "properties": {"OBJECTID": 541431, "GlobalID": "8046cebd-974d-40a8-b304-b6434b84b078", "idInterruption": "SEI-I-45180-1", "panneMajeure": 0}}, {"type": "Feature", "id": 541433, "geometry": {"type": "Point", "coordinates": [-73.225109, 45.964017]}, "properties": {"OBJECTID": 541433, "GlobalID": "7bef609a-a5fb-4319-b220-4d49d2038e1c", "idInterruption": "LAV-I-46036-1", "panneMajeure": 0}}, {"type": "Feature", "id": 541434, "geometry": {"type": "Point", "coordinates": [-73.577717, 45.564747]}, "properties": {"OBJECTID": 541434, "GlobalID": "c0d406ab-cce3-4622-9e8f-2aa4408fe159", "idInterruption": "NOR-I-37875-1", "panneMajeure": 0}}, {"type": "Feature", "id": 541435, "geometry": {"type": "Point", "coordinates": [-72.413745, 45.389164]}, "properties": {"OBJECTID": 541435, "GlobalID": "1b239bfd-c89e-4731-863e-d22ac64924e2", "idInterruption": "SEI-I-45184-1", "panneMajeure": 0}}, {"type": "Feature", "id": 541438, "geometry": {"type": "Point", "coordinates": [-73.355339, 45.482249]}, "properties": {"OBJECTID": 541438, "GlobalID": "1b57d795-094a-4981-a1e4-b5af8d4ac706", "idInterruption": "SEI-I-45187-1", "panneMajeure": 0}}, {"type": "Feature", "id": 541440, "geometry": {"type": "Point", "coordinates": [-73.869296, 45.296553]}, "properties": {"OBJECTID": 541440, "GlobalID": "3d9c869a-052f-401f-b56d-33020e4e2b8b", "idInterruption": "SEI-I-45189-1", "panneMajeure": 0}}, {"type": "Feature", "id": 541441, "geometry": {"type": "Point", "coordinates": [-73.460886, 45.463032]}, "properties": {"OBJECTID": 541441, "GlobalID": "8c8947d3-6082-4a19-92cb-3ae2d9f8ff84", "idInterruption": "SEI-I-45082-1", "panneMajeure": 0}}, {"type": "Feature", "id": 541442, "geometry": {"type": "Point", "coordinates": [-71.71204, 46.324595]}, "properties": {"OBJECTID": 541442, "GlobalID": "306fc7d7-2981-466c-943e-9751af2c050f", "idInterruption": "SEI-I-45186-1", "panneMajeure": 0}}, {"type": "Feature", "id": 541443, "geometry": {"type": "Point", "coordinates": [-74.883746, 46.385424]}, "properties": {"OBJECTID": 541443, "GlobalID": "bc93ca99-c1a2-406d-8c98-91fdf2816b2e", "idInterruption": "LAV-I-46041-1", "panneMajeure": 0}}]}